hashami/__init__.py
hashami/hasher.py
Hashami-1.0.0.dist-info/LICENSE
Hashami-1.0.0.dist-info/METADATA
Hashami-1.0.0.dist-info/WHEEL
Hashami-1.0.0.dist-info/top_level.txt
Hashami-1.0.0.dist-info/RECORD
