Metadata-Version: 2.1
Name: Hashami
Version: 1.0.0
Summary: Deterministic dictionary hashing
Author-email: "James T. Perreault" <james@perreau.lt>
Project-URL: Homepage, https://github.com/jtperreault/hashami
Project-URL: Bug Tracker, https://github.com/jtperreault/hashami/issues
Classifier: Programming Language :: Python :: 3
Classifier: License :: OSI Approved :: MIT License
Classifier: Operating System :: OS Independent
Requires-Python: >=3.7
License-File: LICENSE
